{
  "FileVersion": 2,
  "Id": "60740a81-1a48-47aa-a5a7-72a560eda3b9",
  "Items": [
    {
      "Id": "039b242c-fed3-4239-8dc4-7be44529f2fe",
      "Command": "Network",
      "Items": [
        {
          "Id": "132ecce9-f61d-4364-9404-a3d46a96e982",
          "Command": "-config:debug/disableNetwork:b=yes"
        }
      ]
    },
    {
      "Id": "9d400b2c-c942-4504-89cc-ade420885434",
      "Command": "Difficulty",
      "Items": [
        {
          "Id": "5abe7c99-844a-4d9f-960f-7f08276aa24c",
          "Command": "-config:gameplay/difficulty:t=arcade"
        },
        {
          "Id": "c5cba23c-96a7-481f-8cff-249f3fb32a9e",
          "Command": "-config:gameplay/difficulty:t=realistic"
        },
        {
          "Id": "01e9a28a-6723-41ea-a884-d17aa8e263cc",
          "Command": "-config:gameplay/difficulty:t=hardcore"
        },
        {
          "Id": "11edbb23-bebd-45e9-85e1-abca74d33242",
          "Command": "-config:gameplay/difficulty:t=custom"
        }
      ]
    },
    {
      "Id": "4b348f53-c697-4b89-913f-ef8356bc1874",
      "Command": "Binaries",
      "ExclusiveMode": true,
      "Items": [
        {
          "Id": "76dfd842-77c6-426c-a9c9-50665be097d7",
          "Command": "-config:debug/offlineBinaries:b=yes"
        },
        {
          "Id": "3ce18dcf-b251-425c-9aad-0dc59d6258e1",
          "Command": "-config:debug/offlineBinaries:b=yes -addpath:../gameOnline/ -addpath:../develop/gameBase/pkg_dev/ -addpath:../develop/gameBase/_pc/ -addpath:../develop/gameBase/ -addpath:../develop/gameBase/lang_src/"
        },
        {
          "Id": "701a213f-c67b-4e3f-b236-be19a15239b2",
          "Command": "-config:debug/offlineBinaries:b=no"
        }
      ]
    },
    {
      "Id": "a7345ee9-038e-4864-a5c8-452b0f22ab72",
      "Command": "Console graphics preset",
      "ExclusiveMode": true,
      "Items": [
        {
          "Id": "2415164f-f428-4a46-a6ce-8896bff939e0",
          "Command": "-graphicPreset:HighFPS"
        },
        {
          "Id": "6201449a-56a1-44a4-88ce-08bf05bf5e1d",
          "Command": "-graphicPreset:HighQuality"
        }
      ]
    },
    {
      "Id": "c1c87d75-52d4-476e-a7a5-385ada46da52",
      "Command": "Driver",
      "ExclusiveMode": true,
      "Items": [
        {
          "Id": "5c18e4f4-693b-4ba1-a870-9dd776474e7b",
          "Command": "DX11",
          "Items": [
            {
              "Id": "ec80cbf7-05ff-4d8a-8d90-82f2838371c4",
              "Command": "-config:video/driver:t=dx11"
            },
            {
              "Id": "874cb652-bda3-4c70-8bce-6f1df4ef9ce1",
              "Command": "Debug",
              "ExclusiveMode": true,
              "Items": [
                {
                  "Id": "3685fde5-8d21-40bf-b68e-d1089027af59",
                  "Command": ""
                },
                {
                  "Id": "22a282de-e8a1-4bdf-a45c-932a6510be98",
                  "Command": "-config:directx/debug:b=no"
                },
                {
                  "Id": "292a23d9-4286-4c86-bc08-63368439a8a5",
                  "Command": "-config:directx/debug:b=yes"
                }
              ]
            },
            {
              "Id": "d0cfa318-c905-4cdb-abf6-d94e13334a2d",
              "Command": "ForceDx10",
              "ExclusiveMode": true,
              "Items": [
                {
                  "Id": "7bb9e37e-53f5-415a-b931-53e99030b68c",
                  "Command": ""
                },
                {
                  "Id": "5b1437d5-2ca4-4db7-80ba-aa7c79e325f8",
                  "Command": "-config:directx/forceUseDx10:b=no"
                },
                {
                  "Id": "49a086e1-e00f-4ac4-9ec8-cfaa4a9e393b",
                  "Command": "-config:directx/forceUseDx10:b=yes"
                }
              ]
            }
          ]
        },
        {
          "Id": "24a553cd-d809-405d-9732-3291a224d2fb",
          "Command": "DX12",
          "Items": [
            {
              "Id": "3679ac73-7054-49ce-bee9-91986427feef",
              "Command": "-config:video/driver:t=dx12"
            },
            {
              "Id": "d8003583-9ed9-4047-9f49-459832090280",
              "Command": "Debug level",
              "ExclusiveMode": true,
              "Items": [
                {
                  "Id": "7579e021-ce6a-4c13-adb9-34e5a536dddf",
                  "Command": ""
                },
                {
                  "Id": "6bba0ba2-486d-423b-9493-28f5621bf697",
                  "Command": "-config:dx12/debugLevel:i=0"
                },
                {
                  "Id": "dabca630-960b-4863-9dd4-6b2398634407",
                  "Command": "-config:dx12/debugLevel:i=1"
                },
                {
                  "Id": "64a0769f-2a7e-4003-b7b7-3ce4b2bf5f14",
                  "Command": "-config:dx12/debugLevel:i=2"
                },
                {
                  "Id": "567f367d-d5ee-4109-a8cd-4d2a88fe76b7",
                  "Command": "-config:dx12/debugLevel:i=3"
                }
              ]
            },
            {
              "Id": "83aa8cc6-83f6-479f-b4d4-161521e2b2b3",
              "Command": "Execution mode",
              "ExclusiveMode": true,
              "Items": [
                {
                  "Id": "540d33e8-5239-4868-a449-7a0343c1556c",
                  "Command": ""
                },
                {
                  "Id": "e7c480df-f31d-4432-bbc0-1ef67f10c91b",
                  "Command": "-config:dx12/executionMode:t=concurrent"
                },
                {
                  "Id": "05e041de-a6a6-450e-a4f7-7775a543ebd9",
                  "Command": "-config:dx12/executionMode:t=immediate"
                }
              ]
            },
            {
              "Id": "f94edee9-8a45-4d37-818d-f2a155df053b",
              "Command": "CPU Validation",
              "ExclusiveMode": true,
              "Items": [
                {
                  "Id": "bfbbe853-92c6-4870-8433-01bfcf898c97",
                  "Command": ""
                },
                {
                  "Id": "e65e1955-34dc-4a56-98cf-2d308be30e22",
                  "Command": "-config:dx12/cpuValidation:b=no"
                },
                {
                  "Id": "90ea1c32-267d-40c7-8f6d-f464398938eb",
                  "Command": "-config:dx12/cpuValidation:b=yes"
                }
              ]
            },
            {
              "Id": "e606d2b8-04c2-4158-8a99-12289abb1c40",
              "Command": "GPU Validation",
              "ExclusiveMode": true,
              "Items": [
                {
                  "Id": "9432ed0e-9f72-4dc1-a881-d306fb4b148f",
                  "Command": ""
                },
                {
                  "Id": "6622c2a6-9c0b-4e45-9db1-6826528c1ac0",
                  "Command": "-config:dx12/gpuValidation:b=no"
                },
                {
                  "Id": "2778ae67-26c1-4c5c-91cb-dcb264039d03",
                  "Command": "-config:dx12/gpuValidation:b=yes"
                }
              ]
            },
            {
              "Id": "7e58624d-c4de-4389-a1b1-4ec891bd2788",
              "Command": "Track PageFaults",
              "ExclusiveMode": true,
              "Items": [
                {
                  "Id": "770e803d-7595-413a-9b4b-694ba026e09b",
                  "Command": ""
                },
                {
                  "Id": "e8c09bc8-0ef7-4467-842d-7e3761f0e364",
                  "Command": "-config:dx12/trackPageFaults:b=no"
                },
                {
                  "Id": "6e131857-7b29-49ac-9a32-0c51e878cbd7",
                  "Command": "-config:dx12/trackPageFaults:b=yes"
                }
              ]
            },
            {
              "Id": "1a6f41f3-08e2-473c-9fc4-870108488814",
              "Command": "Breadcrumbs",
              "ExclusiveMode": true,
              "Items": [
                {
                  "Id": "702182e8-4496-4dec-9cc3-c125fa6a1209",
                  "Command": ""
                },
                {
                  "Id": "dd67f3a8-f507-4517-9941-79dcc7086854",
                  "Command": "-config:dx12/placeBreadcrumbs:b=no"
                },
                {
                  "Id": "499a19bc-b80b-4965-b535-8cd791b8e0fa",
                  "Command": "-config:dx12/placeBreadcrumbs:b=yes"
                }
              ]
            },
            {
              "Id": "f204aa9c-646e-46f9-a76d-b24279162f4c",
              "Command": "User barriers",
              "ExclusiveMode": true,
              "Items": [
                {
                  "Id": "49606f03-0c30-4e48-b0cc-7b9ccbf40238",
                  "Command": ""
                },
                {
                  "Id": "53eb7695-b5be-4c24-92c6-35c69df560f7",
                  "Command": "-config:dx12/processUserBarriers:b=no"
                },
                {
                  "Id": "6b91715d-6074-4e18-8394-1631f306dc1e",
                  "Command": "-config:dx12/processUserBarriers:b=yes"
                }
              ]
            },
            {
              "Id": "a07beb14-ca74-4efb-b6bb-245e62a8d707",
              "Command": "Name Objects",
              "ExclusiveMode": true,
              "Items": [
                {
                  "Id": "da72815b-1390-4f83-8c01-f61de91bc079",
                  "Command": ""
                },
                {
                  "Id": "955a216c-79c2-4acd-b7eb-bee1d117a35b",
                  "Command": "-config:dx12/nameObjects:b=no"
                },
                {
                  "Id": "31aee53f-3c7a-4d39-b915-3732454c8b3d",
                  "Command": "-config:dx12/nameObjects:b=yes"
                }
              ]
            },
            {
              "Id": "0e89901b-f9ef-47da-b44d-1d03d3a42b0b",
              "Command": "Enable Markers",
              "ExclusiveMode": true,
              "Items": [
                {
                  "Id": "ce41fb86-5cb4-409b-926f-edb80f32dac5",
                  "Command": ""
                },
                {
                  "Id": "73c3d98f-a56f-4623-8c48-b99d090cf3d3",
                  "Command": "-config:dx12/enableMarkers:b=no"
                },
                {
                  "Id": "18cb74d1-ff99-4df1-8698-b00278215753",
                  "Command": "-config:dx12/enableMarkers:b=yes"
                }
              ]
            },
            {
              "Id": "12b2b0a8-c8ca-4dc9-ae2e-38b7b5e7dea6",
              "Command": "Write Markers",
              "ExclusiveMode": true,
              "Items": [
                {
                  "Id": "7cc66f2f-c0ca-4ea8-ae1a-a3e9bd2f237d",
                  "Command": ""
                },
                {
                  "Id": "4922dd20-27e7-46a5-a5e8-8f737c3b632b",
                  "Command": "-config:dx12/writeMarkers:b=no"
                },
                {
                  "Id": "6ec7164f-51c0-49b4-a539-f71d56b81d4c",
                  "Command": "-config:dx12/writeMarkers:b=yes"
                }
              ]
            },
            {
              "Id": "ad0e46ad-330a-4769-aa20-941a63bbf99a",
              "Command": "Enable PIX Capture",
              "ExclusiveMode": true,
              "Items": [
                {
                  "Id": "c2b776c7-d93b-43ed-96cd-7aa417ce5680",
                  "Command": ""
                },
                {
                  "Id": "e347b3f2-21a3-4568-985a-4bed3b9c9fa0",
                  "Command": "-config:dx12/loadPixCapturer:b=no"
                },
                {
                  "Id": "2f4e7605-7552-45bd-8e7e-0d8fd7e0b24d",
                  "Command": "-config:dx12/loadPixCapturer:b=yes"
                }
              ]
            },
            {
              "Id": "07526d7e-f8b8-48dc-9e35-30920b69ce93",
              "Command": "HDR",
              "ExclusiveMode": true,
              "Items": [
                {
                  "Id": "f4514863-83c3-4227-82a4-8c3113b1edc3",
                  "Command": ""
                },
                {
                  "Id": "0dbdd783-9be9-418d-90e6-7a5f3be0fc3e",
                  "Command": "-config:dx12/forceHdr:b=no"
                },
                {
                  "Id": "da7ddef0-d79a-46f8-ba34-dc962f90221f",
                  "Command": "-config:dx12/forceHdr:b=yes"
                }
              ]
            }
          ]
        },
        {
          "Id": "88f61f06-ed7e-4bf8-8ffd-b6deee1824ae",
          "Command": "Vulkan",
          "Items": [
            {
              "Id": "bb1b855e-a226-45bb-944a-08d90cd77aae",
              "Command": "-config:video/driver:t=vulkan"
            },
            {
              "Id": "7b25aeea-be63-4349-b9ae-2a19fd9546f2",
              "Command": "-config:vulkan/enableRenderDocLayer:b=yes"
            },
            {
              "Id": "e633eb98-e563-4723-ae87-9c650cf7b4bb",
              "Command": "Debug level",
              "ExclusiveMode": true,
              "Items": [
                {
                  "Id": "a6f71623-e276-47fb-9553-a23594709ae3",
                  "Command": ""
                },
                {
                  "Id": "e6b23c1a-8c1c-4441-90b5-7b2b6ede5a83",
                  "Command": "-config:vulkan/debugLevel:i=2"
                }
              ]
            }
          ]
        }
      ]
    },
    {
      "Id": "717a5203-8181-492a-8b32-9a7ef663dd62",
      "Command": "Graphics",
      "Items": [
        {
          "Id": "14968fe9-9735-4071-b784-99efb71b01ce",
          "Command": "-config:graphics/consoleGfxSettings:b=yes"
        },
        {
          "Id": "a325bf92-140c-4740-8f75-743d53b95dbb",
          "Command": "-config:graphics/fluidWind:b=no"
        },
        {
          "Id": "67e654c2-e6aa-41e3-a09e-d3104311eba1",
          "Command": "-config:graphics/prepass:b=no"
        },
        {
          "Id": "283e7ff0-bbad-4440-8daa-b76cc93e4c2e",
          "Command": "-config:graphics/fxTarget:t=highres"
        }
      ]
    },
    {
      "Id": "8345b90f-92c3-4951-80f6-57209c73e9f7",
      "Command": "WindowMode",
      "ExclusiveMode": true,
      "Items": [
        {
          "Id": "3dc621aa-8a9a-45b0-9623-e88467a37838",
          "Command": "-config:video/mode:t=windowed"
        },
        {
          "Id": "a7bcd389-26a2-4e39-a74b-bb0f572a932d",
          "Command": "-config:video/mode:t=fullscreenwindowed"
        },
        {
          "Id": "e90ba9ef-f7cd-4277-a258-743ba354acdb",
          "Command": "-config:video/mode:t=fullscreen"
        }
      ]
    },
    {
      "Id": "f2e43cff-37d9-489b-bd91-2ba63d6a711d",
      "Command": "WindowPosition",
      "ExclusiveMode": true,
      "Items": [
        {
          "Id": "0ad76123-6014-4182-bb45-406fb69bfd49",
          "Command": "-config:video/position:ip2=0,0"
        }
      ]
    },
    {
      "Id": "caf756e6-c739-47d5-82fd-86bfe50faccc",
      "Command": "Resolution",
      "ExclusiveMode": true,
      "Items": [
        {
          "Id": "f1237617-bfeb-49d6-82c0-d432bdc37e83",
          "Command": "-config:video/resolution:t=1920x1080"
        },
        {
          "Id": "315fd12c-023b-48c1-ba5c-fd254552d6f5",
          "Command": "-config:video/resolution:t=1280x720"
        },
        {
          "Id": "807491d3-1c56-4f9c-aa95-282a825f7af0",
          "Command": "-config:video/resolution:t=1024x768"
        },
        {
          "Id": "5035e45f-77c4-4ca7-bd36-c863d227a8b7",
          "Command": "-config:video/resolution:t=854x480"
        }
      ]
    },
    {
      "Id": "973ccf5b-dd6d-422f-9434-2d5d0cc75570",
      "Command": "Map selection",
      "ExclusiveMode": true,
      "Items": [
        {
          "Id": "21160aaa-78d4-44a3-b5dd-f139879a5f14",
          "Command": "training/testFlight/tank/testFlight_ussr_tft",
          "Items": [
            {
              "Id": "e9af2c19-abbf-4d36-b429-3406b310baf2",
              "Command": "-config:game_start/missionFile:t=gameData/missions/training/testFlight/tank/testFlight_ussr_tft.blk -config:debug/disableMenu:b=yes"
            }
          ]
        },
        {
          "Id": "daea7ef8-6ac3-4902-adf1-ecc15e7f337b",
          "Command": "small_mission",
          "Items": [
            {
              "Id": "e111cab8-dbee-42cc-8ed8-2a0cb8af6662",
              "Command": "-config:game_start/missionFile:t=gameData/missions/small_mission.blk -config:debug/disableMenu:b=yes"
            }
          ]
        },
        {
          "Id": "441480fe-4a1e-458d-9f85-6d7d09d9fcdd",
          "Command": "singlemissions/benchmark/benchmark_tank_corpses",
          "Items": [
            {
              "Id": "85326a25-ffa1-43a3-8c09-df851be5b356",
              "Command": "-config:game_start/missionFile:t=gameData/missions/singlemissions/benchmark/benchmark_tank_corpses.blk -config:debug/disableMenu:b=yes"
            }
          ]
        },
        {
          "Id": "7197dfef-25fd-4f2b-a505-159cfdc15f98",
          "Command": "singlemissions/benchmark/benchmark_tank",
          "Items": [
            {
              "Id": "f1ea89d5-4181-4616-95e8-32bac9ed23d8",
              "Command": "-config:game_start/missionFile:t=gameData/missions/singlemissions/benchmark/benchmark_tank.blk -config:debug/disableMenu:b=yes"
            }
          ]
        },
        {
          "Id": "d485de14-90ad-434d-9622-119ed85723a8",
          "Command": "singlemissions/benchmark/benchmark_non-optimized",
          "Items": [
            {
              "Id": "88a74ce0-9594-4087-aff1-6413aee816de",
              "Command": "-config:game_start/missionFile:t=gameData/missions/singlemissions/benchmark/benchmark_non-optimized.blk -config:debug/disableMenu:b=yes"
            }
          ]
        },
        {
          "Id": "38c44602-0db1-4186-ad18-d1dd7550d72e",
          "Command": "singlemissions/tutorial/tutorial_ship_basic",
          "Items": [
            {
              "Id": "3e103014-e63b-4bac-bc8e-2085bd0c3143",
              "Command": "-config:game_start/missionFile:t=gameData/missions/singlemissions/tutorial/tutorial_ship_basic.blk -config:debug/disableMenu:b=yes"
            }
          ]
        },
        {
          "Id": "decd0c2f-8b15-440b-830a-c7bce770e543",
          "Command": "singlemissions/tutorial/tutorial_tank_basic",
          "Items": [
            {
              "Id": "ec130e94-a0db-41fa-a9da-ca5383eabbdd",
              "Command": "-config:game_start/missionFile:t=gameData/missions/singlemissions/tutorial/tutorial_tank_basic.blk -config:debug/disableMenu:b=yes"
            }
          ]
        },
        {
          "Id": "4dbbdaf4-e965-4cbe-8209-fbb569bb1c0d",
          "Command": "singlemissions/qualcomm_demo",
          "Items": [
            {
              "Id": "1e19f5c0-7ac5-4fd3-9c75-d52f9f69801e",
              "Command": "-config:game_start/missionFile:t=gameData/missions/singlemissions/qualcomm_demo.blk -config:debug/disableMenu:b=yes"
            }
          ]
        }
      ]
    },
    {
      "Id": "de575d56-dc76-44bf-a605-b9b1e8f68ee6",
      "Command": "Miscellaneous",
      "Items": [
        {
          "Id": "adf9fa36-4332-413f-bb10-f91163ba6f85",
          "Command": "android_preset",
          "ExclusiveMode": true,
          "Items": [
            {
              "Id": "2b74aefc-2d2c-4634-8b82-113c97c860d2",
              "Command": "-config:shadersPath:t=compiledShaders/gameOculus -config:renderFeaturesPlatform:t=android -config:graphics/use_occlusion:b=no -config:graphics/fluidWind:b=no -config:graphics/prepass:b=no -config:graphics/fxTarget:t=highres -config:graphics/low_res_lut:b=yes"
            }
          ]
        },
        {
          "Id": "ea63b087-10b6-4b3a-bc30-8019283214f7",
          "Command": "-config:debug/devmodeEnabled:b=yes"
        },
        {
          "Id": "d355251c-c953-4795-baf8-fe07d21c7e1f",
          "Command": "-config:debug/ttyconsole:b=yes"
        },
        {
          "Id": "486bb4df-ad42-4f6c-8a37-77f83fb2dbee",
          "Command": "-config:clipmap/cacheWidth:i=8192"
        },
        {
          "Id": "ae3c2022-2397-41ca-a466-4fe37886b77f",
          "Command": "-config:video/forceMSAA:b=yes"
        },
        {
          "Id": "a9284a08-5cba-4664-95ce-9d81484df5c6",
          "Command": "-config:video/preferiGPU:b=yes"
        },
        {
          "Id": "aeb94ea0-44e1-4cd4-a8c2-05541fe43539",
          "Command": "-config:video/threaded_window:b=yes"
        },
        {
          "Id": "044325c5-9ad5-4b5d-b52d-e78395300a97",
          "Command": "-config:video/vsync:b=no"
        },
        {
          "Id": "cf364613-b563-4b0e-b92b-7098e06614b6",
          "Command": "-config:yunetwork/forceAutoLogin:b=yes"
        },
        {
          "Id": "894c933c-2a6d-43fe-bc71-c6423879d0ce",
          "Command": "-rdp_mode"
        }
      ]
    },
    {
      "Id": "c90d23ed-30ed-4858-aaf6-358a02d6f42b",
      "Command": "Profiler",
      "ExclusiveMode": true,
      "Items": [
        {
          "Id": "bc84c548-d76a-47ad-9caf-3fc0cf3d6617",
          "Command": "-config:debug/profiler:t=off"
        },
        {
          "Id": "d186d968-29e2-47cb-aeaa-1c58fa7ab6f6",
          "Command": "-config:debug/profiler:t=cpu"
        },
        {
          "Id": "81d27de6-fc81-4036-b966-aa954d1f6837",
          "Command": "-config:debug/profiler:t=gpu"
        }
      ]
    },
    {
      "Id": "dc7059ac-4287-45a5-adb5-149c9af80e89",
      "Command": "Replay",
      "ExclusiveMode": true,
      "Items": [
        {
          "Id": "1b60fa52-0902-4339-bd61-b0e19f619015",
          "Command": "-play:replay.rpl"
        },
        {
          "Id": "c50fcfac-ba11-46da-b960-5845db44997c",
          "Command": "-record:replay.rpl"
        }
      ]
    },
    {
      "Id": "41b4d135-90cd-4ac3-9c92-9f497d9cd837",
      "Command": "Use addon VromSrc",
      "ExclusiveMode": true,
      "Items": [
        {
          "Id": "480921c8-d3b5-4617-8748-e580749c8fbc",
          "Command": "-config:debug/useAddonVromSrc:b=no"
        },
        {
          "Id": "c7605c34-1f09-49bb-9087-de22c2479d38",
          "Command": "-config:debug/useAddonVromSrc:b=yes"
        },
        {
          "Id": "90bb915f-fb71-4c30-b6bf-2614325c1301",
          "Command": "-config:debug/useAddonVromSrc:b=yes -config:debug/vromfsFirstPriority:b=no"
        }
      ]
    },
    {
      "Id": "a464725b-89d3-4207-83c3-a8e0cab75344",
      "Command": "Webview",
      "Items": [
        {
          "Id": "0fc4d54d-9ea6-424a-b487-4fe5ba504076",
          "Command": "-config:debug/enableWebSocketStream:b=yes"
        },
        {
          "Id": "69420f7f-5a27-43a6-9299-463bde19dffb",
          "Command": "-config:debug/dedicatedWebSocketPort:i=9114"
        },
        {
          "Id": "723f95a1-6d08-4e0b-8141-85231570da89",
          "Command": "-config:debug/WebSocketPort:i=9113"
        },
        {
          "Id": "5eb45a68-b86b-4145-8092-ecace6dbeaed",
          "Command": "-config:debug/dedicatedWebUIPort:i=23457"
        }
      ]
    },
    {
      "Id": "8cb7c892-c547-41b6-9176-cc14947e9c12",
      "Command": "VR mirror",
      "ExclusiveMode": true,
      "Items": [
        {
          "Id": "b6cfda99-1757-43e5-82ce-27fc7f7ef5af",
          "Command": "-config:video/vreye:t=left"
        },
        {
          "Id": "80caa78d-640a-4a73-9638-d56490e8585c",
          "Command": "-config:video/vreye:t=right"
        },
        {
          "Id": "a7db904e-998c-41d5-86ba-8715c2b68245",
          "Command": "-config:video/vreye:t=both"
        }
      ]
    },
    {
      "Id": "0c232f17-22e3-40dd-bc06-9f8dda72dd70",
      "Command": "VR",
      "ExclusiveMode": true,
      "Items": [
        {
          "Id": "f53dab72-5ec6-4615-aebf-803def290b62",
          "Command": "-config:gameplay/enableVR:b=no"
        },
        {
          "Id": "523612af-4c25-483c-a749-3d7886b5d44f",
          "Command": "-config:gameplay/enableVR:b=yes"
        },
        {
          "Id": "e1ca2464-99f0-4bff-bc27-023a5588d9c5",
          "Command": "Emulator",
          "ExclusiveMode": true,
          "Items": [
            {
              "Id": "9410f5dd-f944-45e8-96e0-a61a25441b0f",
              "Command": "-OculusQuest2 -config:gameplay/enableVR:b=yes -config:xr/emulatorProfile:t=2064,2096,0.0681346512074297,-0.907571197,0.785398185,0.837758064,-0.872664630,-0.785398185,0.907571197,0.837758064,-0.872664630"
            }
          ]
        }
      ]
    }
  ]
}